mattes_dada/__init__.py
mattes_dada/cmd.py
mattes_dada/dada.py
mattes_dada/model/__init__.py
mattes_dada/model/dada_text.py
mattes_dada/nltk_data/__init__.py
mattes_dada/nltk_data/nltk_data.py
mattes_dada/odt/__init__.py
mattes_dada/odt/content.py
mattes_dada/odt/handler.py
mattes_dada/odt/styles.py
mattes_dada-0.2.2.dist-info/entry_points.txt
mattes_dada-0.2.2.dist-info/LICENSE.txt
mattes_dada-0.2.2.dist-info/WHEEL
mattes_dada-0.2.2.dist-info/METADATA
mattes_dada-0.2.2.dist-info/RECORD
